Workbook

Sheet Flujo de Caja - Daterra (Actual
A1: PESTAÑA: VALORES GENERALES
A2: Nombre Gasto/Costo | B2: Año 0 | C2: Año 1 | D2: Año 2 | E2: Año 3 | F2: Año 4 | G2: Año 5
A3: Hardware | B3: ='Año 0'!B7 -> 0 | C3: ='Año 1'!B7 -> 0 | D3: 0 | E3: ='Año 3'!B7 -> 6000000 | F3: ='Año 4'!B7 -> 1200000 | G3: ='Año 5'!B7 -> 2000000
A4: Software | B4: ='Año 0'!B5 -> 0 | C4: ='Año 1'!B5 -> 456990 | D4: ='Año 2'!B5 -> 576990 | E4: ='Año 3'!B5 -> 1176990 | F4: ='Año 4'!B5 -> 1656990 | G4: ='Año 5'!B5 -> 1656990
A5: Recursos Humanos | B5: ='Año 0'!B11 -> 0 | C5: ='Año 1'!B11 -> 21600000 | D5: ='Año 2'!B11 -> 21600000 | E5: ='Año 3'!B11 -> 28800000 | F5: ='Año 4'!B12 -> 55200000 | G5: ='Año 5'!B13 -> 69600000
A6: Gastos Operacionales | B6: ='Año 0'!B14 -> 0 | C6: ='Año 1'!B14 -> 1740000 | D6: ='Año 2'!B14 -> 1740000 | E6: ='Año 3'!B14 -> 2700000 | F6: ='Año 4'!B15 -> 2700000 | G6: ='Año 5'!B16 -> 2700000
A7: Marketing | B7: ='Año 0'!B18 -> 0 | C7: ='Año 1'!B18 -> 1000000 | D7: ='Año 2'!B18 -> 1000000 | E7: ='Año 3'!B18 -> 6400000 | F7: ='Año 4'!B19 -> 6400000 | G7: ='Año 5'!B20 -> 9400000
A8: Depreciación Anual de equipos | C8: 200000 | D8: 200000 | E8: 1200000 | F8: =7200000/12 -> 600000 | G8: =9200000/12 -> 766666.67
A9: Total Egresos Anuales | B9: 0 | C9: =SUM(C4:C7) -> 24796990 | D9: =SUM(D4:D7) -> 24916990 | E9: =SUM(E3:E7) -> 45076990 | F9: =SUM(F3:F7) -> 67156990 | G9: =SUM(G3:G7) -> 85356990
A10: Ingresos Anuales (Municipalidades) | B10: 0 | C10: 9600000 | D10: ='Año 2'!B21 -> 36000000 | E10: ='Año 3'!B21 -> 60000000 | F10: ='Año 4'!B22 -> 108000000 | G10: ='Año 5'!B23 -> 156000000
A11: Utilidad Antes del Impuesto | B11: 0 | C11: =SUM(C10,-C9) -> -15196990 | D11: =SUM(D10,-D9) -> 11083010 | E11: =SUM(E10,-E9) -> 14923010 | F11: =SUM(F10,-F9) -> 40843010 | G11: =SUM(G10,-G9) -> 70643010
A12: Préstamo Bancario (Tasa 12% anual) | B12: 0 | C12: 20000000 | D12: 0 | E12: 0 | F12: 0 | G12: 0
A13: Pago Préstamo Bancario (5 años) | B13: 0 | C13: 0 | D13: 5548195 | E13: 5548195 | F13: 5548195 | G13: 5548195
A14: Impuesto (10% ProPyme) | B14: 0 | C14: 0 | D14: =D11*0.1 -> 1108301 | E14: =E11*0.1 -> 1492301 | F14: =F11*0.1 -> 4084301 | G14: =G11*0.1 -> 7064301
A15: Flujo de Caja Neto | B15: 0 | C15: =C11+C12 -> 4803010 | D15: =D11-(D14+D13) -> 4426514 | E15: =E11-(E14+E13) -> 7882514 | F15: =F11-(F14+F13) -> 31210514 | G15: =G11-(G14+G13) -> 58030514
A16: Flujo de Caja Acumulado | B16: 0 | C16: =SUM(B16,C15) -> 4803010 | D16: =C16+D15 -> 9229524 | E16: =D16+E15 -> 17112038 | F16: =E16+F15 -> 48322552 | G16: =F16+G15 -> 106353066

Sheet Año 0
A1: Consolidado Anual
A2: Nombre | B2: Costo/Gasto
A3: Microsoft Office 365 Copilot | B3: 0
A4: AWS | B4: 0
A5: Total Software | B5: =SUM(B3:B4) -> 0
A6: Equipos Computacionales | B6: 0
A7: Total Hardware | B7: =SUM(B6:B6) -> 0
A8: Programador Backend (Fundador) | B8: 0
A9: Programador Frontend (Fundador) | B9: 0
A10: Programador Móvil (Fundador) | B10: 0
A11: Total personal | B11: =SUM(B8:B10) -> 0
A12: Contador | B12: 0
A13: Costos legales | B13: 0
A14: Total Otros | B14: =SUM(B12:B13) -> 0
A15: Google Ads | B15: 0
A16: Viajes y Reuniones | B16: 0
A17: Material Audiovisual Marketing | B17: 0
A18: Total Marketing | B18: =SUM(B15:B17) -> 0
A20: Total Costo/Gasto del periodo | B20: =SUM(B6,B11) -> 0
A21: Ingresos (0 Municipalidad x 1.000.000 mensual) | B21: 0
A23: Total Neto | B23: =SUM(B21,-B20) -> 0

Sheet Año 1
A1: Consolidado Anual
A2: Nombre | B2: Costo/Gasto
A3: Microsoft Office 365 Copilot | B3: 216990
A4: AWS | B4: 240000
A5: Total Software | B5: =SUM(B3:B4) -> 456990
A6: Equipos Computacionales | B6: 0
A7: Total Hardware | B7: =SUM(B6:B6) -> 0
A8: Programador Backend (Fundador) | B8: =600000*12 -> 7200000
A9: Programador Frontend (Fundador) | B9: =600000*12 -> 7200000
A10: Programador Móvil (Fundador) | B10: =600000*12 -> 7200000
A11: Total personal | B11: =SUM(B8:B10) -> 21600000
A12: Contador | B12: =120000*12 -> 1440000
A13: Costos legales | B13: 300000
A14: Total Otros | B14: =SUM(B12:B13) -> 1740000
A15: Google Ads | B15: 0
A16: Viajes y Reuniones | B16: 1000000
A17: Material Audiovisual Marketing | B17: 0
A18: Total Marketing | B18: =SUM(B15:B17) -> 1000000
A20: Total Costo/Gasto del periodo | B20: =SUM(B5,B7,B11,B14,B18) -> 24796990
A21: Ingresos (1 Municipalidad x 1.000.000 mensual) | B21: =1000000*12 -> 12000000
A23: Total Neto | B23: =SUM(B21,-B20) -> -12796990

Sheet Año 2
A1: Consolidado Anual
A2: Nombre | B2: Costo/Gasto
A3: Microsoft Office 365 Copilot | B3: 216990
A4: AWS | B4: 360000
A5: Total Software | B5: =SUM(B3:B4) -> 576990
A6: Equipos Computacionales | B6: 0
A7: Total Hardware | B7: =SUM(B6:B6) -> 0
A8: Programador Backend (Fundador) | B8: =600000*12 -> 7200000
A9: Programador Frontend (Fundador) | B9: =600000*12 -> 7200000
A10: Programador Móvil (Fundador) | B10: =600000*12 -> 7200000
A11: Total personal | B11: =SUM(B8:B10) -> 21600000
A12: Contador | B12: =120000*12 -> 1440000
A13: Costos legales | B13: 300000
A14: Total Otros | B14: =SUM(B12:B13) -> 1740000
A15: Google Ads | B15: 0
A16: Viajes y Reuniones | B16: 1000000
A17: Material Audiovisual Marketing | B17: 0
A18: Total Marketing | B18: =SUM(B15:B17) -> 1000000
A20: Total Costo/Gasto del periodo | B20: =SUM(B5,B11,B7,B14,B18) -> 24916990
A21: Ingresos (3 Municipalidades x 1.000.000 mensual) | B21: =1000000*3*12 -> 36000000
A23: Total Neto | B23: =SUM(B21,-B20) -> 11083010

Sheet Año 3
A1: Consolidado Anual
A2: Nombre | B2: Costo/Gasto
A3: Microsoft Office 365 Copilot | B3: 216990
A4: AWS | B4: 960000
A5: Total Software | B5: =SUM(B3:B4) -> 1176990
A6: Equipos Computacionales | B6: 6000000
A7: Total Hardware | B7: =SUM(B6:B6) -> 6000000
A8: Programador Backend (Fundador) | B8: =800000*12 -> 9600000
A9: Programador Frontend (Fundador) | B9: =800000*12 -> 9600000
A10: Programador Móvil (Fundador) | B10: =800000*12 -> 9600000
A11: Total personal | B11: =SUM(B8:B10) -> 28800000
A12: Contador | B12: =200000*12 -> 2400000
A13: Costos legales | B13: 300000
A14: Total Otros | B14: =SUM(B12:B13) -> 2700000
A15: Google Ads | B15: 400000
A16: Viajes y Reuniones | B16: 4000000
A17: Material Audiovisual Marketing | B17: 2000000
A18: Total Marketing | B18: =SUM(B15:B17) -> 6400000
A20: Total Costo/Gasto del periodo | B20: =SUM(B5,B11,B7,B14,B18) -> 45076990
A21: Ingresos (5 Municipalidades x 1.000.000 mensual) | B21: =1000000*5*12 -> 60000000
A23: Total Neto | B23: =SUM(B21,-B20) -> 14923010

Sheet Año 4
A1: Consolidado Anual
A2: Nombre | B2: Costo/Gasto
A3: Microsoft Office 365 Copilot | B3: 216990
A4: AWS | B4: 1440000
A5: Total Software | B5: =SUM(B3:B4) -> 1656990
A6: Equipos Computacionales | B6: 1200000
A7: Total Hardware | B7: =SUM(B6:B6) -> 1200000
A8: Programador Backend (Fundador) | B8: =1200000*12 -> 14400000
A9: Programador Frontend (Fundador) | B9: =1200000*12 -> 14400000
A10: Programador Móvil (Fundador) | B10: =1200000*12 -> 14400000
A11: Soporte Comercial | B11: =1000000*12 -> 12000000
A12: Total personal | B12: =SUM(B8:B11) -> 55200000
A13: Contador | B13: =200000*12 -> 2400000
A14: Costos legales | B14: 300000
A15: Total Otros | B15: =SUM(B13:B14) -> 2700000
A16: Google Ads | B16: 400000
A17: Viajes y Reuniones | B17: 4000000
A18: Material Audiovisual Marketing | B18: 2000000
A19: Total Marketing | B19: =SUM(B16:B18) -> 6400000
A21: Total Costo/Gasto del periodo | B21: =SUM(B5,B12,B7,B15,B19) -> 67156990
A22: Ingresos (9 Municipalidades x 1.000.000 mensual) | B22: =1000000*9*12 -> 108000000
A24: Total Neto | B24: =SUM(B22,-B21) -> 40843010

Sheet Año 5
A1: Consolidado Anual
A2: Nombre | B2: Costo/Gasto
A3: Microsoft Office 365 Copilot | B3: 216990
A4: AWS | B4: 1440000
A5: Total Software | B5: =SUM(B3:B4) -> 1656990
A6: Equipos Computacionales | B6: 2000000
A7: Total Hardware | B7: =SUM(B6:B6) -> 2000000
A8: Programador Backend (Fundador) | B8: =1600000*12 -> 19200000
A9: Programador Frontend (Fundador) | B9: =1600000*12 -> 19200000
A10: Programador Móvil (Fundador) | B10: =1600000*12 -> 19200000
A11: Soporte Comercial | B11: =1000000*12 -> 12000000
A12: Programador FullStack | B12: =1200000*12 -> 14400000
A13: Total personal | B13: =SUM(B8:B11) -> 69600000
A14: Contador | B14: =200000*12 -> 2400000
A15: Costos legales | B15: 300000
A16: Total Otros | B16: =SUM(B14:B15) -> 2700000
A17: Google Ads | B17: 400000
A18: Viajes y Reuniones | B18: 6000000
A19: Material Audiovisual Marketing | B19: 3000000
A20: Total Marketing | B20: =SUM(B17:B19) -> 9400000
A22: Total Costo/Gasto del periodo | B22: =SUM(B5,B13,B7,B16,B20) -> 85356990
A23: Ingresos (13 Municipalidades x 1.000.000 mensual) | B23: =1000000*13*12 -> 156000000
A25: Total Neto | B25: =SUM(B23,-B22) -> 70643010
